berry_mill/__init__.py
berry_mill/boxbuild.py
berry_mill/builder.py
berry_mill/cfgh.py
berry_mill/kiwiapp.py
berry_mill/kiwrap.py
berry_mill/localrepos.py
berry_mill/localwrap.py
berry_mill/mill.py
berry_mill/params.py
berry_mill/preparer.py
berry_mill/preparetask.py
berry_mill/sysinfo.py
berry_mill/imgdescr/__init__.py
berry_mill/imgdescr/descr.py
berry_mill/imgdescr/loader.py
Berrymill-0.2.dist-info/LICENSE
Berrymill-0.2.dist-info/METADATA
Berrymill-0.2.dist-info/WHEEL
Berrymill-0.2.dist-info/entry_points.txt
Berrymill-0.2.dist-info/top_level.txt
Berrymill-0.2.dist-info/RECORD
