Metadata-Version: 2.1
Name: Berrymill
Version: 0.2
Summary: Kiwi-based Appliance Builder
Home-page: https://github.com/isbm/berrymill
Author: Bo Maryniuk
Author-email: Bo Maryniuk <bo@maryniuk.net>
License: MIT License
Project-URL: Homepage, https://github.com/isbm/berrymill
Keywords: appliance,builder,kiwi
Classifier: License :: OSI Approved :: MIT License
Classifier: Programming Language :: Python
Classifier: Programming Language :: Python :: 3
Requires-Python: >=3.10
License-File: LICENSE
Requires-Dist: inquirer
Requires-Dist: kiwi
Requires-Dist: kiwi-boxed-plugin
Requires-Dist: typing-extensions
Requires-Dist: qemu
Provides-Extra: dev
Requires-Dist: pytest ; extra == 'dev'
Requires-Dist: bumpver ; extra == 'dev'
Requires-Dist: pytest-cov ; extra == 'dev'
Requires-Dist: flake8 ; extra == 'dev'
Requires-Dist: pylint ; extra == 'dev'
